- [字节码指令](#字节码指令)
  - [字节码指令的定义](#字节码指令的定义)
  - [字节码指令与解释器](#字节码指令与解释器)
  - [数据类型与操作类型](#数据类型与操作类型)
  - [字节码指令分类](#字节码指令分类)
    - [加载和存储指令](#加载和存储指令)
    - [运算指令](#运算指令)
    - [类型转换指令](#类型转换指令)
    - [对象创建与访问指令](#对象创建与访问指令)
    - [操作数栈管理指令](#操作数栈管理指令)
    - [控制转移指令](#控制转移指令)
    - [方法调用和返回指令](#方法调用和返回指令)
    - [异常处理指令](#异常处理指令)
    - [同步指令](#同步指令)
  - [字节码表](#字节码表)

# 字节码指令

> 本来不太清楚这一章该怎么写，在看了《深入理解JAVA虚拟机》第二版6.4节后，就清晰了很多，作者很聪明的将多种字节码指令汇总到了一个表格上，并说明了并非每种数据类型和每种操作都有对应的指令（因为表达操作码长度只有一个字节，因此最多只有256个指令）

> 本章与[类文件结构](类文件结构.md)一章是息息相关的，在类文件结构中，我花了大量的篇幅去解释一个类文件中，每个模块的组成部分、二进制数据等。字节码指令属于方法表中的一个属性（Code），它主要描述了方法中的语句

> 解释下操作码和助记符。举个例子，字节码 new x，助记符是new，操作码是0xbb；字节码 getstatic x，助记符是 getstatic，操作码是0xb2。在类文件中，只有操作码，没有助记符，操作码是以十六进制数存在的，助记符是操作码的英文翻译，操作码表示了助记符的索引号，比如第0xbb个助记码是new，那么操作符就是0xbb了

> 这一章更贴近一章手册，且没有太多个人的总结，主要核心部分是：一，字节码指令分类；二，字节码指令表（一些字节码包含代码例子）

### 字节码指令的定义

字节码指令由一个字节长度的、代表某种特定操作含义的数字（称为操作码，Opcode）以及跟随其后的零至多个代表此操作所需参数（称为操作数，Operands）而构成。可以得到这样的公式：**字节码指令 = 操作码 + 操作数**

由于限制了操作码的长度为一个字节（即0 ~ 255），这意味着指令集的操作码总数不可能超过256条

### 字节码指令与解释器

如果不考虑异常处理的话，那么Java虚拟机的解释器可以使用下面这个伪代码来理解

```java
do {
  自动计算PC寄存器的值加1;
  根据PC寄存器的指示位置，从字节码流中取出操作码;
  if (字节码存在操作数) 从字节码流中取出操作数;
  执行操作码所定义的操作;
} while(字节码长度 > 0);
```

解释器执行操作码所定义的操作，在jvm底层实际上需要做大量的工作。用一个字节来代表操作码，也是为了尽可能获得短小精干的编译代码。这种追求尽可能小数据量、高传输效率的设计是由Java语言设计之初面向网络、智能家电的技术背景所决定的，并一直沿用至今

### 数据类型与操作类型

数据类型可分为8种基本类型以及引用类型，在字节码指令中用字母来表示它们，分别是
- z表示boolean
- b表示byte
- c表示char
- s表示short
- i表示int
- f表示float
- l表示long
- d表示double
- a表示reference

同时又有很多种操作类型，如果将所有数据类型与操作类型都对应起来，那字节码指令数量将超过一个字节能表达的范围（256个）

我们不妨来计算一下，以下（axb）表示a种数据类型，b种操作类型
- 将整型0~5推送至栈顶（8x6）
- 将本地变量推送至栈顶（9x1）
- 将数值存入指定本地变量（9x1）
- 将数值存入指定第1至4个本地变量（9x4）
- 将整型数值相加、相减、相乘、相除，并将结果压入栈顶（8x4）
- 将整型数值作取模、取负运算，并将结果压入栈顶（8x2）
- 将整型数值左移位指定位数、数值右（符号）移位指定位数，并将结果压入栈顶（8x2）
- 将整型数值作“按位与”、“按位或”、“按位异或”，并将结果压入栈顶（8x3）
- 将整型类型相互强制转换，并将结果压入栈顶（8x8）
- 比较栈顶两整型数值大小，当结果等于、不等于、小于、小于等于、大于、大于等于0时跳转（8x6）

总共，48 + 9 + 9 + 36 + 32 + 16 + 16 + 24 + 64 + 48 = 302个指令，超过了256个

虽然我上面计算有一些不严谨，但还有很多指令没有考虑进来（可以参考最下面的字节码指令表），总之，可以说明无法把每个数据类型与操作类型对应起来

因此，Java虚拟机规范刻意将一些数据类型不给它设计对应的操作类型，能转换成其他数据类型（主要是int）的，就不设计了，来看下表

表格中以T的模板方式表示数据类型，空白部分表示没有给这一组数据类型与操作类型设计助记符

数据类型与操作类型关系表
|opcode|byte|short|int|long|float|double|char|reference|
|--|--|--|--|--|--|--|--|--|
|Tipush|bipush|sipush|||||||
|Tconst|||iconst|lconst|fconst|dconst||aconst|
|Tload|||iload|lload|fload|dload||aload|
|Tstore|||istore|lstore|fstore|dstore||astore|
|Tinc|||iinc||||||
|Talod|balod|saload|iaload|laload|faload|daload|caload|aaload|
|Tastore|bastore|sastore|iaload|laload|faload|daload|castore|aastore|
|Tadd|||iadd|ladd|fadd|dadd|||
|Tsub|||isub|lsub|fsub|dsub|||
|Tmul|||imul|lmul|fmul|dmul|||
|Tdiv|||idiv|ldiv|fdiv|ddiv|||
|Trem|||irem|lrem|frem|drem|||
|Tneg|||ineg|lneg|fneg|dneg|||
|Tshl|||ishl|lshl|||||
|Tshr|||ishr|lshr|||||
|Tushr|||iushr|lushr|||||
|Tand|||iand|land|||||
|Tor|||ior|lor|||||
|Txor|||ixor|lxor|||||
|i2T|i2b|i2s||i2l|i2f|i2d|||
|l2T|||l2i||l2f|l2d|||
|f2T|||f2i|f2l||f2d|||
|d2T|||d2i|d2l|d2f||||
|Tcmp||||lcmp|||||
|Tcmpl|||||fcmpl|dcmpl|||
|Tcmpg|||||fcmpg|dcmpg|||
|if_TcmpOP|||if_icmpOP|||||if_acmpOp|
|Treturn|||ireturn|lreturn|freturn|dreturn||areturn|

通过表格小结一下
- boolean类型没有助记符
- byte、char、short、reference的助记符很少
- int、long、float、double的助记符较多，尤其是int的
- 编译器会在编译器或者运行期，将byte和short类型的数据带符号拓展（Sign-Extend）为相应的int类型数据，将boolean和char类型数据零位拓展（Zero-Extend）为相应的int类型数据
- 在处理boolean、byte、short和char类型的数组时，也会转换为使用对应的int类型的字节码指令来处理

因此，大多数对于boolean、byte、short和char类型数据的操作，实际上都是使用相应的int类型作为运算类型（Computational Type）

### 字节码指令分类

#### 加载和存储指令

#### 运算指令

#### 类型转换指令

#### 对象创建与访问指令

#### 操作数栈管理指令

#### 控制转移指令

#### 方法调用和返回指令

#### 异常处理指令

#### 同步指令

### 字节码指令表

从 0x00 到 0xc9，字节码指令表一共有202个，大部分都是相似作用的，因此，我不会给每个字节码指令都写Example，只有助记符带了链接（蓝色的）才有，点进去可以看到代码例子

参考
- [JVM字节码指令手册](https://www.cnblogs.com/xpwi/p/11360692.html)
- [维基百科JAVA字节码介绍列表](https://en.wikipedia.org/wiki/Java_bytecode_instruction_listings)

|操作码|助记符|说明|
|--|--|--|
|0x00|nop|什么都不做|
|0x01|aconst_null|将 null 推送至栈顶|
|0x02|iconst_m1|将 int 型 -1 推送至栈顶|
|0x03|iconst_0|将 int 型 0 推送至栈顶|
|0x04|iconst_1|将 int 型 1 推送至栈顶|
|0x05|iconst_2|将 int 型 2 推送至栈顶|
|0x06|iconst_3|将 int 型 3 推送至栈顶|
|0x07|iconst_4|将 int 型 4 推送至栈顶|
|0x08|iconst_5|将 int 型 5 推送至栈顶|
|0x09|lconst_0|将 long 型 0 推送至栈顶|
|0x0a|lconst_1|将 long 型 1 推送至栈顶|
|0x0b|fconst_0|将 float 型 0 推送至栈顶|
|0x0c|fconst_1|将 float 型 1 推送至栈顶|
|0x0d|fconst_2|将 float 型 2 推送至栈顶|
|0x0e|dconst_0|将 double 型 0 推送至栈顶|
|0x0f|dconst_1|将 double 型 1 推送至栈顶|
|0x10|bipush|将单字节的常量值 (-128~127) 推送至栈顶|
|0x11|sipush|将一个短整型常量值 (-32768~32767) 推送至栈顶|
|0x12|ldc|将 int、float 或 String 型常量值从常量池中推送至栈顶|
|0x13|ldc_w|将 int、float 或 String 型常量值从常量池中推送至栈顶（宽索引）|
|0x14|ldc2_w|将 long 或 double 型常量值从常量池中推送至栈顶（宽索引）|
|0x15|iload|将指定的 int 型本地变量推送至栈顶|
|0x16|lload|将指定的 long 型本地变量推送至栈顶|
|0x17|fload|将指定的 float 型本地变量推送至栈顶|
|0x18|dload|将指定的 double 型本地变量推送至栈顶|
|0x19|aload|将指定的引用类型本地变量推送至栈顶|
|0x1a|iload_0|将第一个 int 型本地变量推送至栈顶|
|0x1b|iload_1|将第二个 int 型本地变量推送至栈顶|
|0x1c|iload_2|将第三个 int 型本地变量推送至栈顶|
|0x1d|iload_3|将第四个 int 型本地变量推送至栈顶|
|0x1e|lload_0|将第一个 long 型本地变量推送至栈顶|
|0x1f|lload_1|将第二个 long 型本地变量推送至栈顶|
|0x20|lload_2|将第三个 long 型本地变量推送至栈顶|
|0x21|lload_3|将第四个 long 型本地变量推送至栈顶|
|0x22|fload_0|将第一个 float 型本地变量推送至栈顶|
|0x23|fload_1|将第二个 float 型本地变量推送至栈顶|
|0x24|fload_2|将第三个 float 型本地变量推送至栈顶|
|0x25|fload_3|将第四个 float 型本地变量推送至栈顶|
|0x26|dload_0|将第一个 double 型本地变量推送至栈顶|
|0x27|dload_1|将第二个 double 型本地变量推送至栈顶|
|0x28|dload_2|将第三个 double 型本地变量推送至栈顶|
|0x29|dload_3|将第四个 double 型本地变量推送至栈顶|
|0x2a|aload_0|将第一个引用类型本地变量推送至栈顶|
|0x2b|aload_1|将第二个引用类型本地变量推送至栈顶|
|0x2c|aload_2|将第三个引用类型本地变量推送至栈顶|
|0x2d|aload_3|将第四个引用类型本地变量推送至栈顶|
|0x2e|iaload|将 int 型数组指定索引的值推送至栈顶|
|0x2f|laload|将 long 型数组指定索引的值推送至栈顶|
|0x30|faload|将 float 型数组指定索引的值推送至栈顶|
|0x31|daload|将 double 型数组指定索引的值推送至栈顶|
|0x32|aaload|将引用型数组指定索引的值推送至栈顶|
|0x33|baload|将 boolean 或 byte 型数组指定索引的值推送至栈顶|
|0x34|caload|将 char 型数组指定索引的值推送至栈顶|
|0x35|saload|将 short 型数组指定索引的值推送至栈顶|
|0x36|istore|将栈顶 int 型数值存入指定本地变量|
|0x37|lstore|将栈顶 long 型数值存入指定本地变量|
|0x38|fstore|将栈顶 float 型数值存入指定本地变量|
|0x39|dstore|将栈顶 double 型数值存入指定本地变量|
|0x3a|astore|将栈顶引用型数值存入指定本地变量|
|0x3b|istore_0|将栈顶 int 型数值存入第一个本地变量|
|0x3c|istore_1|将栈顶 int 型数值存入第二个本地变量|
|0x3d|istore_2|将栈顶 int 型数值存入第三个本地变量|
|0x3e|istore_3|将栈顶 int 型数值存入第四个本地变量|
|0x3f|lstore_0|将栈顶 long 型数值存入第一个本地变量|
|0x40|lstore_1|将栈顶 long 型数值存入第二个本地变量|
|0x41|lstore_2|将栈顶 long 型数值存入第三个本地变量|
|0x42|lstore_3|将栈顶 long 型数值存入第四个本地变量|
|0x43|fstore_0|将栈顶 float 型数值存入第一个本地变量|
|0x44|fstore_1|将栈顶 float 型数值存入第二个本地变量|
|0x45|fstore_2|将栈顶 float 型数值存入第三个本地变量|
|0x46|fstore_3|将栈顶 float 型数值存入第四个本地变量|
|0x47|dstore_0|将栈顶 double 型数值存入第一个本地变量|
|0x48|dstore_1|将栈顶 double 型数值存入第二个本地变量|
|0x49|dstore_2|将栈顶 double 型数值存入第三个本地变量|
|0x4a|dstore_3|将栈顶 double 型数值存入第四个本地变量|
|0x4b|astore_0|将栈顶引用型数值存入第一个本地变量|
|0x4c|astore_1|将栈顶引用型数值存入第二个本地变量|
|0x4d|astore_2|将栈顶引用型数值存入第三个本地变量|
|0x4e|astore_3|将栈顶引用型数值存入第四个本地变量|
|0x4f|iastore|将栈顶 int 型数值存入指定数组的指定索引位置|
|0x50|lastore|将栈顶 long 型数值存入指定数组的指定索引位置|
|0x51|fastore|将栈顶 float 型数值存入指定数组的指定索引位置|
|0x52|dastore|将栈顶 double 型数值存入指定数组的指定索引位置|
|0x53|aastore|将栈顶引用型数值存入指定数组的指定索引位置|
|0x54|bastore|将栈顶 boolean 或 byte 型数值存入指定数组的指定索引位置|
|0x55|castore|将栈顶 char 型数值存入指定数组的指定索引位置|
|0x56|sastore|将栈顶 short 型数值存入指定数组的指定索引位置|
|0x57|pop|将栈顶数值弹出|
|0x58|pop2|将栈顶的一个（long 或 double 类型的)或两个数值弹出（其它）|
|0x59|dup|复制栈顶数值并将复制值压入栈顶|
|0x5a|dup_x1|复制栈顶数值并将两个复制值压入栈顶|
|0x5b|dup_x2|复制栈顶数值并将三个（或两个）复制值压入栈顶|
|0x5c|dup2|复制栈顶一个（long 或 double 类型的)或两个（其它）数值并将复制值压入栈顶|
|0x5d|dup2_x1|dup_x1 指令的双倍版本|
|0x5e|dup2_x2|dup_x2 指令的双倍版本|
|0x5f|swap|将栈最顶端的两个数值互换(数值不能是 long 或 double 类型的)|
|0x60|iadd|将栈顶两 int 型数值相加并将结果压入栈顶|
|0x61|ladd|将栈顶两 long 型数值相加并将结果压入栈顶|
|0x62|fadd|将栈顶两 float 型数值相加并将结果压入栈顶|
|0x63|dadd|将栈顶两 double 型数值相加并将结果压入栈顶|
|0x64|isub|将栈顶两 int 型数值相减并将结果压入栈顶|
|0x65|lsub|将栈顶两 long 型数值相减并将结果压入栈顶|
|0x66|fsub|将栈顶两 float 型数值相减并将结果压入栈顶|
|0x67|dsub|将栈顶两 double 型数值相减并将结果压入栈顶|
|0x68|imul|将栈顶两 int 型数值相乘并将结果压入栈顶|
|0x69|lmul|将栈顶两 long 型数值相乘并将结果压入栈顶|
|0x6a|fmul|将栈顶两 float 型数值相乘并将结果压入栈顶|
|0x6b|dmul|将栈顶两 double 型数值相乘并将结果压入栈顶|
|0x6c|idiv|将栈顶两 int 型数值相除并将结果压入栈顶|
|0x6d|ldiv|将栈顶两 long 型数值相除并将结果压入栈顶|
|0x6e|fdiv|将栈顶两 float 型数值相除并将结果压入栈顶|
|0x6f|ddiv|将栈顶两 double 型数值相除并将结果压入栈顶|
|0x70|irem|将栈顶两 int 型数值作取模运算并将结果压入栈顶|
|0x71|lrem|将栈顶两 long 型数值作取模运算并将结果压入栈顶|
|0x72|frem|将栈顶两 float 型数值作取模运算并将结果压入栈顶|
|0x73|drem|将栈顶两 double 型数值作取模运算并将结果压入栈顶|
|0x74|ineg|将栈顶 int 型数值取负并将结果压入栈顶|
|0x75|lneg|将栈顶 long 型数值取负并将结果压入栈顶|
|0x76|fneg|将栈顶 float 型数值取负并将结果压入栈顶|
|0x77|dneg|将栈顶 double 型数值取负并将结果压入栈顶|
|0x78|ishl|将 int 型数值左移位指定位数并将结果压入栈顶|
|0x79|lshl|将 long 型数值左移位指定位数并将结果压入栈顶|
|0x7a|ishr|将 int 型数值右（符号）移位指定位数并将结果压入栈顶|
|0x7b|lshr|将 long 型数值右（符号）移位指定位数并将结果压入栈顶|
|0x7c|iushr|将 int 型数值右（无符号）移位指定位数并将结果压入栈顶|
|0x7d|lushr|将 long 型数值右（无符号）移位指定位数并将结果压入栈顶|
|0x7e|iand|将栈顶两 int 型数值作“按位与”并将结果压入栈顶|
|0x7f|land|将栈顶两 long 型数值作“按位与”并将结果压入栈顶|
|0x80|ior|将栈顶两 int 型数值作“按位或”并将结果压入栈顶|
|0x81|lor|将栈顶两 long 型数值作“按位或”并将结果压入栈顶|
|0x82|ixor|将栈顶两 int 型数值作“按位异或”并将结果压入栈顶|
|0x83|lxor|将栈顶两 long 型数值作“按位异或”并将结果压入栈顶|
|0x84|iinc|将指定 int 型变量增加指定值（如 i++、i--、i+=2 等）|
|0x85|i2l|将栈顶 int 型数值强制转换成 long 型数值并将结果压入栈顶|
|0x86|i2f|将栈顶 int 型数值强制转换成 float 型数值并将结果压入栈顶|
|0x87|i2d|将栈顶 int 型数值强制转换成 double 型数值并将结果压入栈顶|
|0x88|l2i|将栈顶 long 型数值强制转换成 int 型数值并将结果压入栈顶|
|0x89|l2f|将栈顶 long 型数值强制转换成 float 型数值并将结果压入栈顶|
|0x8a|l2d|将栈顶  long 型数值强制转换成 double 型数值并将结果压入栈顶|
|0x8b|f2i|将栈顶 float 型数值强制转换成 int 型数值并将结果压入栈顶|
|0x8c|f2l|将栈顶 float 型数值强制转换成 long 型数值并将结果压入栈顶|
|0x8d|f2d|将栈顶 float 型数值强制转换成 double 型数值并将结果压入栈顶|
|0x8e|d2i|将栈顶 double 型数值强制转换成 int 型数值并将结果压入栈顶|
|0x8f|d2l|将栈顶 double 型数值强制转换成 long 型数值并将结果压入栈顶|
|0x90|d2f|将栈顶 double 型数值强制转换成 float 型数值并将结果压入栈顶|
|0x91|i2b|将栈顶 int 型数值强制转换成 byte 型数值并将结果压入栈顶|
|0x92|i2c|将栈顶 int 型数值强制转换成 char 型数值并将结果压入栈顶|
|0x93|i2s|将栈顶 int 型数值强制转换成 short 型数值并将结果压入栈顶|
|0x94|lcmp|比较栈顶两 long 型数值大小，并将结果（1，0，-1）压入栈顶|
|0x95|fcmpl|比较栈顶两 float 型数值大小，并将结果（1，0，-1）压入栈顶；当其中一个数值为 NaN 时，将 -1 压入栈顶|
|0x96|fcmpg|比较栈顶两 float 型数值大小，并将结果（1，0，-1）压入栈顶；当其中一个数值为 NaN 时，将 1 压入栈顶|
|0x97|dcmpl|比较栈顶两 double 型数值大小，并将结果（1，0，-1）压入栈顶；当其中一个数值为 NaN 时，将 -1 压入栈顶|
|0x98|dcmpg|比较栈顶两 double 型数值大小，并将结果（1，0，-1）压入栈顶；当其中一个数值为 NaN 时，将 1 压入栈顶|
|0x99|ifeq|当栈顶 int 型数值等于 0 时跳转|
|0x9a|ifne|当栈顶 int 型数值不等于 0 时跳转|
|0x9b|iflt|当栈顶 int 型数值小于 0 时跳转|
|0x9c|ifge|当栈顶 int 型数值大于等于 0 时跳转|
|0x9d|ifgt|当栈顶 int 型数值大于 0 时跳转|
|0x9e|ifle|当栈顶 int 型数值小于等于 0 时跳转|
|0x9f|if_icmpeq|比较栈顶两 int 型数值大小，当结果等于 0 时跳转|
|0xa0|if_icmpne|比较栈顶两 int 型数值大小，当结果不等于 0 时跳转|
|0xa1|if_icmplt|比较栈顶两 int 型数值大小，当结果小于 0 时跳转|
|0xa2|if_icmpge|比较栈顶两 int 型数值大小，当结果大于等于 0 时跳转|
|0xa3|if_icmpgt|比较栈顶两 int 型数值大小，当结果大于 0 时跳转|
|0xa4|if_icmple|比较栈顶两 int 型数值大小，当结果小于等于 0 时跳转|
|0xa5|if_acmpeq|比较栈顶两引用型数值，当结果相等时跳转|
|0xa6|if_acmpne|比较栈顶两引用型数值，当结果不相等时跳转|
|0xa7|goto|无条件跳转|
|0xa8|jsr|跳转至指定 16 位 offset 位置，并将 jsr 下一条指令地址压入栈顶|
|0xa9|ret|返回至本地变量指定的 index 的指令位置（一般与 jsr, jsr_w 联合使用）|
|0xaa|tableswitch|用于 switch 条件跳转，case 值连续（可变长度指令）|
|0xab|lookupswitch|用于 switch 条件跳转，case 值不连续（可变长度指令）|
|0xac|ireturn|从当前方法返回 int|
|0xad|lreturn|从当前方法返回 long|
|0xae|freturn|从当前方法返回 float|
|0xaf|dreturn|从当前方法返回 double|
|0xb0|areturn|从当前方法返回对象引用|
|0xb1|return|从当前方法返回 void|
|0xb2|[getstatic](ByteCodeExample/getstatic.md)|获取指定类的静态域，并将其值压入栈顶|
|0xb3|[putstatic](ByteCodeExample/putstatic.md)|为指定的类的静态域赋值|
|0xb4|getfield|获取指定类的实例域，并将其值压入栈顶|
|0xb5|putfield|为指定的类的实例域赋值|
|0xb6|invokevirtual|调用实例方法|
|0xb7|invokespecial|调用超类构造方法，实例初始化方法，私有方法|
|0xb8|[invokestatic](ByteCodeExample/invokestatic.md)|调用静态方法|
|0xb9|invokeinterface|调用接口方法|
|0xba|invokedynamic|调用动态方法|
|0xbb|[new](ByteCodeExample/new.md)|创建一个对象，并将其引用值压入栈顶|
|0xbc|newarray|创建一个指定原始类型（如int, float, char…）的数组，并将其引用值压入栈顶|
|0xbd|[anewarray](ByteCodeExample/anewarray.md)|创建一个引用型（如类，接口，数组）的数组，并将其引用值压入栈顶|
|0xbe|arraylength|获得数组的长度值并压入栈顶|
|0xbf|athrow|将栈顶的异常抛出|
|0xc0|checkcast|检验类型转换，检验未通过将抛出 ClassCastException|
|0xc1|instanceof|检验对象是否是指定的类的实例，如果是将 1 压入栈顶，否则将0压入栈顶|
|0xc2|monitorenter|获得对象的锁，用于同步方法或同步块|
|0xc3|monitorexit|释放对象的锁，用于同步方法或同步块|
|0xc4|wide|拓展本地变量的宽度|
|0xc5|multianewarray|创建指定类型和指定维度的多维数组（执行该指令时，操作栈中必须包含各维度的长度值），并将其引用值压入栈顶|
|0xc6|ifnull|为 null 时跳转|
|0xc7|ifnonnull|不为 null 时跳转|
|0xc8|goto_w|无条件跳转（宽索引）|
|0xc9|jsr_w|跳转至指定 32 位 offset 位置，并将 jsr_w 下一条指令地址压入栈顶|
